aiohttp/__init__.py
aiohttp/_cparser.pxd
aiohttp/_find_header.pxd
aiohttp/_headers.pxi
aiohttp/_helpers.cpython-312.so
aiohttp/_helpers.pyi
aiohttp/_helpers.pyx
aiohttp/_http_parser.cpython-312.so
aiohttp/_http_parser.pyx
aiohttp/_http_writer.cpython-312.so
aiohttp/_http_writer.pyx
aiohttp/_websocket.cpython-312.so
aiohttp/_websocket.pyx
aiohttp/abc.py
aiohttp/base_protocol.py
aiohttp/client.py
aiohttp/client_exceptions.py
aiohttp/client_proto.py
aiohttp/client_reqrep.py
aiohttp/client_ws.py
aiohttp/compression_utils.py
aiohttp/connector.py
aiohttp/cookiejar.py
aiohttp/formdata.py
aiohttp/hdrs.py
aiohttp/helpers.py
aiohttp/http.py
aiohttp/http_exceptions.py
aiohttp/http_parser.py
aiohttp/http_websocket.py
aiohttp/http_writer.py
aiohttp/log.py
aiohttp/multipart.py
aiohttp/payload.py
aiohttp/payload_streamer.py
aiohttp/py.typed
aiohttp/pytest_plugin.py
aiohttp/resolver.py
aiohttp/streams.py
aiohttp/tcp_helpers.py
aiohttp/test_utils.py
aiohttp/tracing.py
aiohttp/typedefs.py
aiohttp/web.py
aiohttp/web_app.py
aiohttp/web_exceptions.py
aiohttp/web_fileresponse.py
aiohttp/web_log.py
aiohttp/web_middlewares.py
aiohttp/web_protocol.py
aiohttp/web_request.py
aiohttp/web_response.py
aiohttp/web_routedef.py
aiohttp/web_runner.py
aiohttp/web_server.py
aiohttp/web_urldispatcher.py
aiohttp/web_ws.py
aiohttp/worker.py
aiohttp_qpython-3.10.10.1.dist-info/METADATA
aiohttp_qpython-3.10.10.1.dist-info/WHEEL
aiohttp_qpython-3.10.10.1.dist-info/top_level.txt
aiohttp_qpython-3.10.10.1.dist-info/RECORD
