Metadata-Version: 2.4
Name: aiohttp-qpython
Version: 3.10.10.1
Summary: Async http client/server framework (asyncio)
Author-email: The QPYPI Team <qpypi@qpython.org>
License: MIT AND (Apache-2.0 OR BSD-2-Clause)
Project-URL: Homepage, https://qpypi.qpython.org/project/aiohttp-qpython/
Classifier: Intended Audience :: Developers
Classifier: Intended Audience :: Education
Classifier: Intended Audience :: Information Technology
Classifier: Intended Audience :: End Users/Desktop
Classifier: License :: OSI Approved :: Apache Software License
Classifier: Operating System :: Android
Classifier: Programming Language :: Python
Classifier: Programming Language :: Python :: 3.12
Classifier: Topic :: Software Development
Requires-Python: ==3.12.*
Requires-Dist: multidict
Requires-Dist: yarl
Requires-Dist: async_timeout
Requires-Dist: aiosignal
Requires-Dist: aiohappyeyeballs
